pg_stream_copy/__init__.py
pg_stream_copy/encoder.py
pg_stream_copy/protocol.py
pg_stream_copy/py.typed
pg_stream_copy/schema.py
pg_stream_copy/writer.py
pg_stream_copy/writer_encoder.py
pg_stream_copy-3.0.0.dist-info/LICENCE.md
pg_stream_copy-3.0.0.dist-info/METADATA
pg_stream_copy-3.0.0.dist-info/WHEEL
pg_stream_copy-3.0.0.dist-info/RECORD
